{
    "initial_probs": [
        2.1194566215854138e-05,
        0.99997878074646
    ],
    "initial_logits": [
        -4.850401878356934,
        5.911342620849609
    ],
    "regression_weights": [
        [
            [
                -0.0,
                18.14265251159668
            ],
            [
                -5.283326148986816,
                0.0
            ]
        ],
        [
            [
                0.0,
                0.6885654926300049
            ],
            [
                0.3405689597129822,
                0.0
            ]
        ]
    ],
    "regression_intercepts": [
        [
            [
                -0.0,
                -3.9553608894348145
            ],
            [
                -1.4342564344406128,
                0.0
            ]
        ]
    ],
    "transition_probs": [
        [
            [
                1.7715419833671864e-29,
                1.0
            ],
            [
                2.5418716020908505e-09,
                1.0
            ]
        ],
        [
            [
                1.1030633041506082e-30,
                1.0
            ],
            [
                1.1752323558766875e-09,
                1.0
            ]
        ],
        [
            [
                4.2781689018233455e-31,
                1.0
            ],
            [
                8.664098882782412e-10,
                1.0
            ]
        ],
        [
            [
                5.999493239901935e-31,
                1.0
            ],
            [
                1.005962202427213e-09,
                1.0
            ]
        ],
        [
            [
                3.8301338943690146e-29,
                1.0
            ],
            [
                3.1044085080367267e-09,
                1.0
            ]
        ],
        [
            [
                1.2220793800244709e-30,
                1.0
            ],
            [
                1.2222650669357904e-09,
                1.0
            ]
        ],
        [
            [
                2.1216151942652325e-31,
                1.0
            ],
            [
                7.618149444610367e-10,
                1.0
            ]
        ],
        [
            [
                8.051268200554587e-32,
                1.0
            ],
            [
                5.868542318765435e-10,
                1.0
            ]
        ],
        [
            [
                4.421203900787334e-30,
                1.0
            ],
            [
                1.7395032081424233e-09,
                1.0
            ]
        ],
        [
            [
                2.960259648817015e-31,
                1.0
            ],
            [
                8.379964500093706e-10,
                1.0
            ]
        ],
        [
            [
                7.093411926809643e-32,
                1.0
            ],
            [
                5.696563776247388e-10,
                1.0
            ]
        ],
        [
            [
                3.309532051837575e-32,
                1.0
            ],
            [
                4.640708095582369e-10,
                1.0
            ]
        ],
        [
            [
                4.6661806850806213e-29,
                1.0
            ],
            [
                3.316857233315318e-09,
                1.0
            ]
        ],
        [
            [
                6.0814773881034246e-31,
                1.0
            ],
            [
                1.0269032291176927e-09,
                1.0
            ]
        ],
        [
            [
                5.3000941315864115e-30,
                1.0
            ],
            [
                1.8518186983840224e-09,
                1.0
            ]
        ],
        [
            [
                1.3886848274738595e-31,
                1.0
            ],
            [
                6.9206512742781e-10,
                1.0
            ]
        ],
        [
            [
                2.0970003719463726e-32,
                1.0
            ],
            [
                4.156683885980783e-10,
                1.0
            ]
        ],
        [
            [
                7.358580677152104e-33,
                1.0
            ],
            [
                3.1343277973050476e-10,
                1.0
            ]
        ],
        [
            [
                3.809580295711271e-33,
                1.0
            ],
            [
                2.6317478751813894e-10,
                1.0
            ]
        ],
        [
            [
                2.3651153886765742e-33,
                1.0
            ],
            [
                2.3148008509998874e-10,
                1.0
            ]
        ],
        [
            [
                1.773282819383346e-33,
                1.0
            ],
            [
                2.1431410812677854e-10,
                1.0
            ]
        ],
        [
            [
                1.393735805476488e-33,
                1.0
            ],
            [
                2.0149504287303444e-10,
                1.0
            ]
        ],
        [
            [
                1.046619027669886e-33,
                1.0
            ],
            [
                1.866245630255392e-10,
                1.0
            ]
        ],
        [
            [
                8.176738704319832e-34,
                1.0
            ],
            [
                1.749564382258484e-10,
                1.0
            ]
        ],
        [
            [
                6.5107638254871755e-34,
                1.0
            ],
            [
                1.6479018150050706e-10,
                1.0
            ]
        ],
        [
            [
                5.234979143553111e-34,
                1.0
            ],
            [
                1.5557446997327418e-10,
                1.0
            ]
        ],
        [
            [
                8.095670001731404e-34,
                1.0
            ],
            [
                1.0671663552841437e-10,
                1.0
            ]
        ],
        [
            [
                9.513581146425252e-29,
                1.0
            ],
            [
                4.114579787994899e-09,
                1.0
            ]
        ],
        [
            [
                2.411085145033754e-31,
                1.0
            ],
            [
                8.125921047152929e-10,
                1.0
            ]
        ],
        [
            [
                1.5326656644573502e-32,
                1.0
            ],
            [
                3.8358591303300216e-10,
                1.0
            ]
        ],
        [
            [
                5.1240044871473216e-33,
                1.0
            ],
            [
                2.84286927332289e-10,
                1.0
            ]
        ],
        [
            [
                3.550783826776221e-33,
                1.0
            ],
            [
                2.5667903913451084e-10,
                1.0
            ]
        ],
        [
            [
                3.523151628008235e-33,
                1.0
            ],
            [
                2.553727507237369e-10,
                1.0
            ]
        ],
        [
            [
                4.454128622865248e-38,
                1.0
            ],
            [
                1.6466347382837476e-11,
                1.0
            ]
        ],
        [
            [
                0.0,
                NaN
            ],
            [
                4.547046062158139e-13,
                1.0
            ]
        ],
        [
            [
                0.0,
                NaN
            ],
            [
                7.217575875070187e-14,
                1.0
            ]
        ],
        [
            [
                0.0,
                NaN
            ],
            [
                2.694126863332473e-14,
                1.0
            ]
        ],
        [
            [
                0.0,
                NaN
            ],
            [
                1.5374405240120396e-14,
                1.0
            ]
        ],
        [
            [
                0.0,
                NaN
            ],
            [
                6.5986911674555376e-15,
                1.0
            ]
        ],
        [
            [
                2.7275983138001985e-38,
                1.0
            ],
            [
                1.481276733217296e-11,
                1.0
            ]
        ],
        [
            [
                0.0,
                NaN
            ],
            [
                2.7435836263446645e-13,
                1.0
            ]
        ],
        [
            [
                0.0,
                NaN
            ],
            [
                3.6341497980417817e-14,
                1.0
            ]
        ],
        [
            [
                0.0,
                NaN
            ],
            [
                1.3152431990466184e-14,
                1.0
            ]
        ],
        [
            [
                0.0,
                NaN
            ],
            [
                7.590383366057243e-15,
                1.0
            ]
        ],
        [
            [
                0.0,
                NaN
            ],
            [
                5.5137071835597174e-15,
                1.0
            ]
        ],
        [
            [
                0.0,
                NaN
            ],
            [
                4.717005357547741e-15,
                1.0
            ]
        ],
        [
            [
                0.0,
                NaN
            ],
            [
                4.38271660513378e-15,
                1.0
            ]
        ],
        [
            [
                0.0,
                NaN
            ],
            [
                4.242142170174509e-15,
                1.0
            ]
        ],
        [
            [
                0.0,
                NaN
            ],
            [
                4.1896816081027875e-15,
                1.0
            ]
        ],
        [
            [
                0.0,
                NaN
            ],
            [
                4.176724121592165e-15,
                1.0
            ]
        ],
        [
            [
                0.0,
                NaN
            ],
            [
                2.1733626640859987e-15,
                1.0
            ]
        ],
        [
            [
                0.0,
                NaN
            ],
            [
                3.729364907167909e-12,
                1.0
            ]
        ],
        [
            [
                0.0,
                NaN
            ],
            [
                1.1760393819806175e-13,
                1.0
            ]
        ],
        [
            [
                0.0,
                NaN
            ],
            [
                2.2118840708128772e-14,
                1.0
            ]
        ],
        [
            [
                0.0,
                NaN
            ],
            [
                9.972690635264275e-15,
                1.0
            ]
        ],
        [
            [
                0.0,
                NaN
            ],
            [
                6.952055101841666e-15,
                1.0
            ]
        ],
        [
            [
                0.0,
                NaN
            ],
            [
                5.992474345786845e-15,
                1.0
            ]
        ],
        [
            [
                0.0,
                NaN
            ],
            [
                6.3599066503939195e-15,
                1.0
            ]
        ],
        [
            [
                0.0,
                NaN
            ],
            [
                7.060779827434754e-15,
                1.0
            ]
        ],
        [
            [
                0.0,
                NaN
            ],
            [
                7.657623382509131e-15,
                1.0
            ]
        ],
        [
            [
                0.0,
                NaN
            ],
            [
                8.158808542234764e-15,
                1.0
            ]
        ],
        [
            [
                0.0,
                NaN
            ],
            [
                8.974073518802292e-15,
                1.0
            ]
        ],
        [
            [
                2.4331151052107067e-36,
                1.0
            ],
            [
                2.0741618492192693e-11,
                1.0
            ]
        ],
        [
            [
                4.489480123131223e-20,
                1.0
            ],
            [
                5.155814619683952e-07,
                0.9999995231628418
            ]
        ],
        [
            [
                8.371817128427494e-10,
                1.0
            ],
            [
                0.00018579105380922556,
                0.9998142123222351
            ]
        ],
        [
            [
                0.9809659719467163,
                0.01903405226767063
            ],
            [
                0.1919044852256775,
                0.8080954551696777
            ]
        ],
        [
            [
                0.9741610288619995,
                0.02583892084658146
            ],
            [
                0.21702946722507477,
                0.7829704880714417
            ]
        ],
        [
            [
                0.9809659719467163,
                0.01903405226767063
            ],
            [
                0.1919044852256775,
                0.8080954551696777
            ]
        ],
        [
            [
                6.323371604749779e-17,
                1.0
            ],
            [
                1.4444567568716593e-06,
                0.9999985694885254
            ]
        ],
        [
            [
                0.9809659719467163,
                0.01903405226767063
            ],
            [
                0.1919044852256775,
                0.8080954551696777
            ]
        ],
        [
            [
                0.9809659719467163,
                0.01903405226767063
            ],
            [
                0.1919044852256775,
                0.8080954551696777
            ]
        ],
        [
            [
                0.9809659719467163,
                0.01903405226767063
            ],
            [
                0.1919044852256775,
                0.8080954551696777
            ]
        ],
        [
            [
                3.792525755247356e-12,
                1.0
            ],
            [
                3.557022864697501e-05,
                0.9999644756317139
            ]
        ],
        [
            [
                0.9809659719467163,
                0.01903405226767063
            ],
            [
                0.1919044852256775,
                0.8080954551696777
            ]
        ],
        [
            [
                0.9809659719467163,
                0.01903405226767063
            ],
            [
                0.1919044852256775,
                0.8080954551696777
            ]
        ],
        [
            [
                0.9809659719467163,
                0.01903405226767063
            ],
            [
                0.1919044852256775,
                0.8080954551696777
            ]
        ],
        [
            [
                6.737132770230526e-23,
                1.0
            ],
            [
                2.633055906642312e-08,
                1.0
            ]
        ],
        [
            [
                0.9809659719467163,
                0.01903405226767063
            ],
            [
                0.1919044852256775,
                0.8080954551696777
            ]
        ],
        [
            [
                1.4534932368803766e-08,
                1.0
            ],
            [
                0.00039307764382101595,
                0.9996069073677063
            ]
        ],
        [
            [
                0.9809659719467163,
                0.01903405226767063
            ],
            [
                0.1919044852256775,
                0.8080954551696777
            ]
        ],
        [
            [
                0.9809659719467163,
                0.01903405226767063
            ],
            [
                0.1919044852256775,
                0.8080954551696777
            ]
        ],
        [
            [
                0.9809659719467163,
                0.01903405226767063
            ],
            [
                0.1919044852256775,
                0.8080954551696777
            ]
        ],
        [
            [
                0.9809659719467163,
                0.01903405226767063
            ],
            [
                0.1919044852256775,
                0.8080954551696777
            ]
        ],
        [
            [
                0.9809659719467163,
                0.01903405226767063
            ],
            [
                0.1919044852256775,
                0.8080954551696777
            ]
        ],
        [
            [
                0.9809659719467163,
                0.01903405226767063
            ],
            [
                0.1919044852256775,
                0.8080954551696777
            ]
        ],
        [
            [
                0.9809659719467163,
                0.01903405226767063
            ],
            [
                0.1919044852256775,
                0.8080954551696777
            ]
        ],
        [
            [
                0.9809659719467163,
                0.01903405226767063
            ],
            [
                0.1919044852256775,
                0.8080954551696777
            ]
        ],
        [
            [
                0.9809659719467163,
                0.01903405226767063
            ],
            [
                0.1919044852256775,
                0.8080954551696777
            ]
        ],
        [
            [
                0.9809659719467163,
                0.01903405226767063
            ],
            [
                0.1919044852256775,
                0.8080954551696777
            ]
        ],
        [
            [
                0.9809659719467163,
                0.01903405226767063
            ],
            [
                0.1919044852256775,
                0.8080954551696777
            ]
        ],
        [
            [
                0.5461034774780273,
                0.45389655232429504
            ],
            [
                0.6036595106124878,
                0.3963405191898346
            ]
        ],
        [
            [
                0.9809659719467163,
                0.01903405226767063
            ],
            [
                0.1919044852256775,
                0.8080954551696777
            ]
        ],
        [
            [
                0.9809659719467163,
                0.01903405226767063
            ],
            [
                0.1919044852256775,
                0.8080954551696777
            ]
        ],
        [
            [
                0.9809659719467163,
                0.01903405226767063
            ],
            [
                0.1919044852256775,
                0.8080954551696777
            ]
        ],
        [
            [
                0.9809659719467163,
                0.01903405226767063
            ],
            [
                0.1919044852256775,
                0.8080954551696777
            ]
        ],
        [
            [
                0.9809659719467163,
                0.01903405226767063
            ],
            [
                0.1919044852256775,
                0.8080954551696777
            ]
        ],
        [
            [
                0.9809659719467163,
                0.01903405226767063
            ],
            [
                0.1919044852256775,
                0.8080954551696777
            ]
        ],
        [
            [
                0.9809659719467163,
                0.01903405226767063
            ],
            [
                0.1919044852256775,
                0.8080954551696777
            ]
        ],
        [
            [
                0.9809659719467163,
                0.01903405226767063
            ],
            [
                0.1919044852256775,
                0.8080954551696777
            ]
        ],
        [
            [
                0.9809659719467163,
                0.01903405226767063
            ],
            [
                0.1919044852256775,
                0.8080954551696777
            ]
        ],
        [
            [
                0.9809659719467163,
                0.01903405226767063
            ],
            [
                0.1919044852256775,
                0.8080954551696777
            ]
        ],
        [
            [
                0.9809659719467163,
                0.01903405226767063
            ],
            [
                0.1919044852256775,
                0.8080954551696777
            ]
        ],
        [
            [
                0.7141538858413696,
                0.28584611415863037
            ],
            [
                0.5148268342018127,
                0.48517316579818726
            ]
        ],
        [
            [
                0.0008709921385161579,
                0.9991289973258972
            ],
            [
                0.00959092192351818,
                0.9904090166091919
            ]
        ],
        [
            [
                0.9809659719467163,
                0.01903405226767063
            ],
            [
                0.1919044852256775,
                0.8080954551696777
            ]
        ],
        [
            [
                0.9809659719467163,
                0.01903405226767063
            ],
            [
                0.1919044852256775,
                0.8080954551696777
            ]
        ],
        [
            [
                0.9809659719467163,
                0.01903405226767063
            ],
            [
                0.1919044852256775,
                0.8080954551696777
            ]
        ],
        [
            [
                0.9809659719467163,
                0.01903405226767063
            ],
            [
                0.1919044852256775,
                0.8080954551696777
            ]
        ],
        [
            [
                0.9809659719467163,
                0.01903405226767063
            ],
            [
                0.1919044852256775,
                0.8080954551696777
            ]
        ],
        [
            [
                0.9809659719467163,
                0.01903405226767063
            ],
            [
                0.1919044852256775,
                0.8080954551696777
            ]
        ],
        [
            [
                0.9809659719467163,
                0.01903405226767063
            ],
            [
                0.1919044852256775,
                0.8080954551696777
            ]
        ],
        [
            [
                0.9809659719467163,
                0.01903405226767063
            ],
            [
                0.1919044852256775,
                0.8080954551696777
            ]
        ],
        [
            [
                0.9809659719467163,
                0.01903405226767063
            ],
            [
                0.1919044852256775,
                0.8080954551696777
            ]
        ],
        [
            [
                0.9809659719467163,
                0.01903405226767063
            ],
            [
                0.1919044852256775,
                0.8080954551696777
            ]
        ],
        [
            [
                0.8647275567054749,
                0.13527245819568634
            ],
            [
                0.4000282287597656,
                0.5999718308448792
            ]
        ],
        [
            [
                0.9809659719467163,
                0.01903405226767063
            ],
            [
                0.1919044852256775,
                0.8080954551696777
            ]
        ],
        [
            [
                0.9809659719467163,
                0.01903405226767063
            ],
            [
                0.1919044852256775,
                0.8080954551696777
            ]
        ],
        [
            [
                0.9809659719467163,
                0.01903405226767063
            ],
            [
                0.1919044852256775,
                0.8080954551696777
            ]
        ],
        [
            [
                0.9809659719467163,
                0.01903405226767063
            ],
            [
                0.1919044852256775,
                0.8080954551696777
            ]
        ],
        [
            [
                0.9809659719467163,
                0.01903405226767063
            ],
            [
                0.1919044852256775,
                0.8080954551696777
            ]
        ],
        [
            [
                0.9809659719467163,
                0.01903405226767063
            ],
            [
                0.1919044852256775,
                0.8080954551696777
            ]
        ],
        [
            [
                0.9809659719467163,
                0.01903405226767063
            ],
            [
                0.1919044852256775,
                0.8080954551696777
            ]
        ],
        [
            [
                0.9809659719467163,
                0.01903405226767063
            ],
            [
                0.1919044852256775,
                0.8080954551696777
            ]
        ],
        [
            [
                0.9809659719467163,
                0.01903405226767063
            ],
            [
                0.1919044852256775,
                0.8080954551696777
            ]
        ],
        [
            [
                0.9809659719467163,
                0.01903405226767063
            ],
            [
                0.1919044852256775,
                0.8080954551696777
            ]
        ],
        [
            [
                0.9809659719467163,
                0.01903405226767063
            ],
            [
                0.1919044852256775,
                0.8080954551696777
            ]
        ],
        [
            [
                0.0,
                NaN
            ],
            [
                1.0228785049873346e-12,
                1.0
            ]
        ],
        [
            [
                3.04120724609995e-31,
                1.0
            ],
            [
                8.24590784542778e-10,
                1.0
            ]
        ]
    ],
    "transition_logits": [
        [
            [
                0.0,
                66.20311737060547
            ],
            [
                -19.79036521911621,
                0.0
            ]
        ],
        [
            [
                0.0,
                68.97946166992188
            ],
            [
                -20.561800003051758,
                0.0
            ]
        ],
        [
            [
                0.0,
                69.9266128540039
            ],
            [
                -20.866662979125977,
                0.0
            ]
        ],
        [
            [
                0.0,
                69.58846282958984
            ],
            [
                -20.717321395874023,
                0.0
            ]
        ],
        [
            [
                0.0,
                65.43206787109375
            ],
            [
                -19.590442657470703,
                0.0
            ]
        ],
        [
            [
                0.0,
                68.87699890136719
            ],
            [
                -20.522560119628906,
                0.0
            ]
        ],
        [
            [
                0.0,
                70.62796020507812
            ],
            [
                -20.995317459106445,
                0.0
            ]
        ],
        [
            [
                0.0,
                71.59689331054688
            ],
            [
                -21.256244659423828,
                0.0
            ]
        ],
        [
            [
                0.0,
                67.59114074707031
            ],
            [
                -20.169666290283203,
                0.0
            ]
        ],
        [
            [
                0.0,
                70.29486083984375
            ],
            [
                -20.900007247924805,
                0.0
            ]
        ],
        [
            [
                0.0,
                71.72355651855469
            ],
            [
                -21.285987854003906,
                0.0
            ]
        ],
        [
            [
                0.0,
                72.48591613769531
            ],
            [
                -21.490983963012695,
                0.0
            ]
        ],
        [
            [
                0.0,
                65.23462677001953
            ],
            [
                -19.524248123168945,
                0.0
            ]
        ],
        [
            [
                0.0,
                69.57489013671875
            ],
            [
                -20.696718215942383,
                0.0
            ]
        ],
        [
            [
                0.0,
                67.40982818603516
            ],
            [
                -20.107097625732422,
                0.0
            ]
        ],
        [
            [
                0.0,
                71.0517807006836
            ],
            [
                -21.091341018676758,
                0.0
            ]
        ],
        [
            [
                0.0,
                72.94221496582031
            ],
            [
                -21.601133346557617,
                0.0
            ]
        ],
        [
            [
                0.0,
                73.98944091796875
            ],
            [
                -21.88343620300293,
                0.0
            ]
        ],
        [
            [
                0.0,
                74.64778900146484
            ],
            [
                -22.058202743530273,
                0.0
            ]
        ],
        [
            [
                0.0,
                75.12448120117188
            ],
            [
                -22.186527252197266,
                0.0
            ]
        ],
        [
            [
                0.0,
                75.4124755859375
            ],
            [
                -22.263578414916992,
                0.0
            ]
        ],
        [
            [
                0.0,
                75.6533203125
            ],
            [
                -22.32525634765625,
                0.0
            ]
        ],
        [
            [
                0.0,
                75.93974304199219
            ],
            [
                -22.40192222595215,
                0.0
            ]
        ],
        [
            [
                0.0,
                76.18659973144531
            ],
            [
                -22.46648406982422,
                0.0
            ]
        ],
        [
            [
                0.0,
                76.41443634033203
            ],
            [
                -22.526348114013672,
                0.0
            ]
        ],
        [
            [
                0.0,
                76.63253021240234
            ],
            [
                -22.58389663696289,
                0.0
            ]
        ],
        [
            [
                0.0,
                76.19656372070312
            ],
            [
                -22.960844039916992,
                0.0
            ]
        ],
        [
            [
                0.0,
                64.52224731445312
            ],
            [
                -19.30872917175293,
                0.0
            ]
        ],
        [
            [
                0.0,
                70.50006103515625
            ],
            [
                -20.9307918548584,
                0.0
            ]
        ],
        [
            [
                0.0,
                73.2557144165039
            ],
            [
                -21.68145751953125,
                0.0
            ]
        ],
        [
            [
                0.0,
                74.35137176513672
            ],
            [
                -21.981037139892578,
                0.0
            ]
        ],
        [
            [
                0.0,
                74.7181396484375
            ],
            [
                -22.083194732666016,
                0.0
            ]
        ],
        [
            [
                0.0,
                74.7259521484375
            ],
            [
                -22.08829689025879,
                0.0
            ]
        ],
        [
            [
                0.0,
                86.00440216064453
            ],
            [
                -24.829702377319336,
                0.0
            ]
        ],
        [
            [
                0.0,
                99.27445220947266
            ],
            [
                -28.41912841796875,
                0.0
            ]
        ],
        [
            [
                0.0,
                106.08329010009766
            ],
            [
                -30.259672164916992,
                0.0
            ]
        ],
        [
            [
                0.0,
                109.7448501586914
            ],
            [
                -31.2451171875,
                0.0
            ]
        ],
        [
            [
                0.0,
                111.83485412597656
            ],
            [
                -31.806072235107422,
                0.0
            ]
        ],
        [
            [
                0.0,
                112.11441040039062
            ],
            [
                -32.65190505981445,
                0.0
            ]
        ],
        [
            [
                0.0,
                86.49481201171875
            ],
            [
                -24.935531616210938,
                0.0
            ]
        ],
        [
            [
                0.0,
                101.2451171875
            ],
            [
                -28.924341201782227,
                0.0
            ]
        ],
        [
            [
                0.0,
                108.71204376220703
            ],
            [
                -30.945816040039062,
                0.0
            ]
        ],
        [
            [
                0.0,
                112.47698974609375
            ],
            [
                -31.962169647216797,
                0.0
            ]
        ],
        [
            [
                0.0,
                114.51920318603516
            ],
            [
                -32.51189422607422,
                0.0
            ]
        ],
        [
            [
                0.0,
                115.70024108886719
            ],
            [
                -32.831539154052734,
                0.0
            ]
        ],
        [
            [
                0.0,
                116.27559661865234
            ],
            [
                -32.98760223388672,
                0.0
            ]
        ],
        [
            [
                0.0,
                116.54617309570312
            ],
            [
                -33.06110763549805,
                0.0
            ]
        ],
        [
            [
                0.0,
                116.66574096679688
            ],
            [
                -33.09370803833008,
                0.0
            ]
        ],
        [
            [
                0.0,
                116.71131134033203
            ],
            [
                -33.10615158081055,
                0.0
            ]
        ],
        [
            [
                0.0,
                116.72187805175781
            ],
            [
                -33.109249114990234,
                0.0
            ]
        ],
        [
            [
                0.0,
                115.39265441894531
            ],
            [
                -33.76250076293945,
                0.0
            ]
        ],
        [
            [
                0.0,
                91.63643646240234
            ],
            [
                -26.314783096313477,
                0.0
            ]
        ],
        [
            [
                0.0,
                104.39441680908203
            ],
            [
                -29.771453857421875,
                0.0
            ]
        ],
        [
            [
                0.0,
                110.55683135986328
            ],
            [
                -31.442346572875977,
                0.0
            ]
        ],
        [
            [
                0.0,
                113.49079132080078
            ],
            [
                -32.23892593383789,
                0.0
            ]
        ],
        [
            [
                0.0,
                114.8160171508789
            ],
            [
                -32.59973907470703,
                0.0
            ]
        ],
        [
            [
                0.0,
                115.35066223144531
            ],
            [
                -32.74827194213867,
                0.0
            ]
        ],
        [
            [
                0.0,
                115.09686279296875
            ],
            [
                -32.68876266479492,
                0.0
            ]
        ],
        [
            [
                0.0,
                114.70404815673828
            ],
            [
                -32.58422088623047,
                0.0
            ]
        ],
        [
            [
                0.0,
                114.39993286132812
            ],
            [
                -32.503074645996094,
                0.0
            ]
        ],
        [
            [
                0.0,
                114.1499252319336
            ],
            [
                -32.43967819213867,
                0.0
            ]
        ],
        [
            [
                0.0,
                113.78919982910156
            ],
            [
                -32.34443664550781,
                0.0
            ]
        ],
        [
            [
                0.0,
                82.00389099121094
            ],
            [
                -24.598878860473633,
                0.0
            ]
        ],
        [
            [
                0.0,
                44.549964904785156
            ],
            [
                -14.477970123291016,
                0.0
            ]
        ],
        [
            [
                0.0,
                20.90097999572754
            ],
            [
                -8.590702056884766,
                0.0
            ]
        ],
        [
            [
                0.0,
                -3.942308187484741
            ],
            [
                -1.4376825094223022,
                0.0
            ]
        ],
        [
            [
                0.0,
                -3.629694700241089
            ],
            [
                -1.2830618619918823,
                0.0
            ]
        ],
        [
            [
                0.0,
                -3.942308187484741
            ],
            [
                -1.4376825094223022,
                0.0
            ]
        ],
        [
            [
                0.0,
                37.2996940612793
            ],
            [
                -13.447775840759277,
                0.0
            ]
        ],
        [
            [
                0.0,
                -3.942308187484741
            ],
            [
                -1.4376825094223022,
                0.0
            ]
        ],
        [
            [
                0.0,
                -3.942308187484741
            ],
            [
                -1.4376825094223022,
                0.0
            ]
        ],
        [
            [
                0.0,
                -3.942308187484741
            ],
            [
                -1.4376825094223022,
                0.0
            ]
        ],
        [
            [
                0.0,
                26.297988891601562
            ],
            [
                -10.243966102600098,
                0.0
            ]
        ],
        [
            [
                0.0,
                -3.942308187484741
            ],
            [
                -1.4376825094223022,
                0.0
            ]
        ],
        [
            [
                0.0,
                -3.942308187484741
            ],
            [
                -1.4376825094223022,
                0.0
            ]
        ],
        [
            [
                0.0,
                -3.942308187484741
            ],
            [
                -1.4376825094223022,
                0.0
            ]
        ],
        [
            [
                0.0,
                51.051822662353516
            ],
            [
                -17.45253562927246,
                0.0
            ]
        ],
        [
            [
                0.0,
                -3.942308187484741
            ],
            [
                -1.4376825094223022,
                0.0
            ]
        ],
        [
            [
                0.0,
                18.046710968017578
            ],
            [
                -7.8411102294921875,
                0.0
            ]
        ],
        [
            [
                0.0,
                -3.942308187484741
            ],
            [
                -1.4376825094223022,
                0.0
            ]
        ],
        [
            [
                0.0,
                -3.942308187484741
            ],
            [
                -1.4376825094223022,
                0.0
            ]
        ],
        [
            [
                0.0,
                -3.942308187484741
            ],
            [
                -1.4376825094223022,
                0.0
            ]
        ],
        [
            [
                0.0,
                -3.942308187484741
            ],
            [
                -1.4376825094223022,
                0.0
            ]
        ],
        [
            [
                0.0,
                -3.942308187484741
            ],
            [
                -1.4376825094223022,
                0.0
            ]
        ],
        [
            [
                0.0,
                -3.942308187484741
            ],
            [
                -1.4376825094223022,
                0.0
            ]
        ],
        [
            [
                0.0,
                -3.942308187484741
            ],
            [
                -1.4376825094223022,
                0.0
            ]
        ],
        [
            [
                0.0,
                -3.942308187484741
            ],
            [
                -1.4376825094223022,
                0.0
            ]
        ],
        [
            [
                0.0,
                -3.942308187484741
            ],
            [
                -1.4376825094223022,
                0.0
            ]
        ],
        [
            [
                0.0,
                -3.942308187484741
            ],
            [
                -1.4376825094223022,
                0.0
            ]
        ],
        [
            [
                0.0,
                -3.942308187484741
            ],
            [
                -1.4376825094223022,
                0.0
            ]
        ],
        [
            [
                0.0,
                -0.18493914604187012
            ],
            [
                0.42073655128479004,
                0.0
            ]
        ],
        [
            [
                0.0,
                -3.942308187484741
            ],
            [
                -1.4376825094223022,
                0.0
            ]
        ],
        [
            [
                0.0,
                -3.942308187484741
            ],
            [
                -1.4376825094223022,
                0.0
            ]
        ],
        [
            [
                0.0,
                -3.942308187484741
            ],
            [
                -1.4376825094223022,
                0.0
            ]
        ],
        [
            [
                0.0,
                -3.942308187484741
            ],
            [
                -1.4376825094223022,
                0.0
            ]
        ],
        [
            [
                0.0,
                -3.942308187484741
            ],
            [
                -1.4376825094223022,
                0.0
            ]
        ],
        [
            [
                0.0,
                -3.942308187484741
            ],
            [
                -1.4376825094223022,
                0.0
            ]
        ],
        [
            [
                0.0,
                -3.942308187484741
            ],
            [
                -1.4376825094223022,
                0.0
            ]
        ],
        [
            [
                0.0,
                -3.942308187484741
            ],
            [
                -1.4376825094223022,
                0.0
            ]
        ],
        [
            [
                0.0,
                -3.942308187484741
            ],
            [
                -1.4376825094223022,
                0.0
            ]
        ],
        [
            [
                0.0,
                -3.942308187484741
            ],
            [
                -1.4376825094223022,
                0.0
            ]
        ],
        [
            [
                0.0,
                -3.942308187484741
            ],
            [
                -1.4376825094223022,
                0.0
            ]
        ],
        [
            [
                0.0,
                -0.9156448841094971
            ],
            [
                0.05932474136352539,
                0.0
            ]
        ],
        [
            [
                0.0,
                7.045006275177002
            ],
            [
                -4.637300968170166,
                0.0
            ]
        ],
        [
            [
                0.0,
                -3.942308187484741
            ],
            [
                -1.4376825094223022,
                0.0
            ]
        ],
        [
            [
                0.0,
                -3.942308187484741
            ],
            [
                -1.4376825094223022,
                0.0
            ]
        ],
        [
            [
                0.0,
                -3.942308187484741
            ],
            [
                -1.4376825094223022,
                0.0
            ]
        ],
        [
            [
                0.0,
                -3.942308187484741
            ],
            [
                -1.4376825094223022,
                0.0
            ]
        ],
        [
            [
                0.0,
                -3.942308187484741
            ],
            [
                -1.4376825094223022,
                0.0
            ]
        ],
        [
            [
                0.0,
                -3.942308187484741
            ],
            [
                -1.4376825094223022,
                0.0
            ]
        ],
        [
            [
                0.0,
                -3.942308187484741
            ],
            [
                -1.4376825094223022,
                0.0
            ]
        ],
        [
            [
                0.0,
                -3.942308187484741
            ],
            [
                -1.4376825094223022,
                0.0
            ]
        ],
        [
            [
                0.0,
                -3.942308187484741
            ],
            [
                -1.4376825094223022,
                0.0
            ]
        ],
        [
            [
                0.0,
                -3.942308187484741
            ],
            [
                -1.4376825094223022,
                0.0
            ]
        ],
        [
            [
                0.0,
                -1.855123519897461
            ],
            [
                -0.4053475856781006,
                0.0
            ]
        ],
        [
            [
                0.0,
                -3.942308187484741
            ],
            [
                -1.4376825094223022,
                0.0
            ]
        ],
        [
            [
                0.0,
                -3.942308187484741
            ],
            [
                -1.4376825094223022,
                0.0
            ]
        ],
        [
            [
                0.0,
                -3.942308187484741
            ],
            [
                -1.4376825094223022,
                0.0
            ]
        ],
        [
            [
                0.0,
                -3.942308187484741
            ],
            [
                -1.4376825094223022,
                0.0
            ]
        ],
        [
            [
                0.0,
                -3.942308187484741
            ],
            [
                -1.4376825094223022,
                0.0
            ]
        ],
        [
            [
                0.0,
                -3.942308187484741
            ],
            [
                -1.4376825094223022,
                0.0
            ]
        ],
        [
            [
                0.0,
                -3.942308187484741
            ],
            [
                -1.4376825094223022,
                0.0
            ]
        ],
        [
            [
                0.0,
                -3.942308187484741
            ],
            [
                -1.4376825094223022,
                0.0
            ]
        ],
        [
            [
                0.0,
                -3.942308187484741
            ],
            [
                -1.4376825094223022,
                0.0
            ]
        ],
        [
            [
                0.0,
                -3.942308187484741
            ],
            [
                -1.4376825094223022,
                0.0
            ]
        ],
        [
            [
                0.0,
                -3.942308187484741
            ],
            [
                -1.4376825094223022,
                0.0
            ]
        ],
        [
            [
                0.0,
                96.06558227539062
            ],
            [
                -27.608400344848633,
                0.0
            ]
        ],
        [
            [
                0.0,
                70.26788330078125
            ],
            [
                -20.916133880615234,
                0.0
            ]
        ]
    ],
    "posterior_probs": [
        [
            1.0202093108091503e-06,
            0.999998927116394
        ],
        [
            1.363685414590421e-10,
            1.0
        ],
        [
            2.665508924692972e-10,
            1.0
        ],
        [
            4.720188240270318e-09,
            1.0
        ],
        [
            5.977213168861795e-11,
            1.0
        ],
        [
            4.4908049501302116e-10,
            1.0
        ],
        [
            1.4755083266315694e-10,
            1.0
        ],
        [
            5.681824455372464e-11,
            1.0
        ],
        [
            3.8039599248307354e-11,
            1.0
        ],
        [
            1.9005837181840235e-10,
            1.0
        ],
        [
            1.35216504659752e-10,
            1.0
        ],
        [
            3.776027754365252e-11,
            1.0
        ],
        [
            2.0437079112367584e-11,
            1.0
        ],
        [
            1.259952558951838e-10,
            1.0
        ],
        [
            3.231966083649951e-10,
            1.0
        ],
        [
            1.3695450329365144e-10,
            1.0
        ],
        [
            1.434159041524552e-11,
            1.0
        ],
        [
            9.414603124868748e-11,
            1.0
        ],
        [
            1.4637848225196315e-11,
            1.0
        ],
        [
            4.4072870353240035e-11,
            1.0
        ],
        [
            1.0379630314971688e-11,
            1.0
        ],
        [
            1.4547002491482885e-11,
            1.0
        ],
        [
            5.6190149755330765e-11,
            1.0
        ],
        [
            1.3888852568033627e-10,
            1.0
        ],
        [
            1.3422405548135785e-11,
            1.0
        ],
        [
            1.990555636988134e-11,
            1.0
        ],
        [
            9.53295428707257e-12,
            1.0
        ],
        [
            2.2818448519590362e-10,
            1.0
        ],
        [
            2.0333672523520363e-09,
            1.0
        ],
        [
            4.336807302163237e-11,
            1.0
        ],
        [
            2.849894487066962e-10,
            1.0
        ],
        [
            5.94850696478133e-11,
            1.0
        ],
        [
            4.1650065341070075e-11,
            1.0
        ],
        [
            2.331648207842818e-10,
            1.0
        ],
        [
            3.8722740292040925e-11,
            1.0
        ],
        [
            2.5854407156855608e-11,
            1.0
        ],
        [
            9.596910939546621e-13,
            1.0
        ],
        [
            1.4884916758363398e-13,
            1.0
        ],
        [
            7.133583410394093e-14,
            1.0
        ],
        [
            2.8249289097726817e-14,
            1.0
        ],
        [
            4.902172556775497e-10,
            1.0
        ],
        [
            3.0776611727872938e-12,
            1.0
        ],
        [
            3.776254211673019e-13,
            1.0
        ],
        [
            4.619457231693673e-15,
            1.0
        ],
        [
            9.385855621494655e-16,
            1.0
        ],
        [
            2.971290464410007e-16,
            1.0
        ],
        [
            2.7968967037843913e-16,
            1.0
        ],
        [
            5.222501279700188e-16,
            1.0
        ],
        [
            7.603797826842909e-16,
            1.0
        ],
        [
            7.792316655957378e-16,
            1.0
        ],
        [
            2.619595237869529e-16,
            1.0
        ],
        [
            3.925403993367216e-16,
            1.0
        ],
        [
            1.8392482903448887e-13,
            1.0
        ],
        [
            1.5948537724296517e-14,
            1.0
        ],
        [
            4.70001387662582e-15,
            1.0
        ],
        [
            5.652991481461202e-16,
            1.0
        ],
        [
            5.746307513073432e-16,
            1.0
        ],
        [
            2.751434857318477e-16,
            1.0
        ],
        [
            6.047770774165974e-16,
            1.0
        ],
        [
            6.895082712897276e-16,
            1.0
        ],
        [
            1.3241431012783614e-15,
            1.0
        ],
        [
            2.450483786461228e-16,
            1.0
        ],
        [
            4.2117291875055473e-16,
            1.0
        ],
        [
            2.3303297225912845e-12,
            1.0
        ],
        [
            2.234940126299989e-07,
            0.9999997615814209
        ],
        [
            1.0673225915525109e-05,
            0.9999892711639404
        ],
        [
            0.024212565273046494,
            0.9757874011993408
        ],
        [
            0.12322378158569336,
            0.8767762184143066
        ],
        [
            0.6256275177001953,
            0.3743724524974823
        ],
        [
            5.597565433390628e-08,
            1.0
        ],
        [
            0.059268925338983536,
            0.9407310485839844
        ],
        [
            0.15345598757266998,
            0.8465440273284912
        ],
        [
            0.7381576895713806,
            0.261842280626297
        ],
        [
            1.0212167580903042e-05,
            0.9999897480010986
        ],
        [
            0.1397261917591095,
            0.8602737784385681
        ],
        [
            0.11301930993795395,
            0.8869807720184326
        ],
        [
            0.1357915699481964,
            0.8642084002494812
        ],
        [
            1.2882831468274958e-09,
            1.0
        ],
        [
            0.03794948384165764,
            0.9620504975318909
        ],
        [
            1.128545250139723e-06,
            0.999998927116394
        ],
        [
            0.0009084437624551356,
            0.9990915060043335
        ],
        [
            0.0035494554322212934,
            0.9964505434036255
        ],
        [
            0.00450618052855134,
            0.9954937696456909
        ],
        [
            0.0021240958012640476,
            0.9978759288787842
        ],
        [
            0.00828983448445797,
            0.9917102456092834
        ],
        [
            0.1831834465265274,
            0.8168165683746338
        ],
        [
            0.8342655897140503,
            0.1657344251871109
        ],
        [
            0.917608916759491,
            0.08239112049341202
        ],
        [
            0.9975113868713379,
            0.0024886513128876686
        ],
        [
            0.9982788562774658,
            0.001721181208267808
        ],
        [
            0.9991099238395691,
            0.0008901148103177547
        ],
        [
            0.9892907738685608,
            0.010709267109632492
        ],
        [
            0.9988226294517517,
            0.0011773973237723112
        ],
        [
            0.9997771382331848,
            0.00022282240388449281
        ],
        [
            0.9996899366378784,
            0.00031011816463433206
        ],
        [
            0.9965925812721252,
            0.0034073807764798403
        ],
        [
            0.9998486042022705,
            0.00015141397307161242
        ],
        [
            0.9998993873596191,
            0.00010063566878670827
        ],
        [
            0.9999649524688721,
            3.50442023773212e-05
        ],
        [
            0.9996552467346191,
            0.00034478516317903996
        ],
        [
            0.9989607334136963,
            0.0010392089607194066
        ],
        [
            0.9975698590278625,
            0.002430180087685585
        ],
        [
            0.9473878741264343,
            0.05261210724711418
        ],
        [
            0.12290841341018677,
            0.8770915269851685
        ],
        [
            0.0001520668010925874,
            0.9998478889465332
        ],
        [
            0.036351051181554794,
            0.9636489152908325
        ],
        [
            0.49770548939704895,
            0.5022945404052734
        ],
        [
            0.9875866174697876,
            0.012413399294018745
        ],
        [
            0.9994262456893921,
            0.0005737440078519285
        ],
        [
            0.9994003772735596,
            0.0005996550316922367
        ],
        [
            0.9995276927947998,
            0.0004723643360193819
        ],
        [
            0.9962263107299805,
            0.0037736650556325912
        ],
        [
            0.9991569519042969,
            0.0008430470479652286
        ],
        [
            0.9999903440475464,
            9.622990546631627e-06
        ],
        [
            0.9987422823905945,
            0.0012577148154377937
        ],
        [
            0.8699555993080139,
            0.13004443049430847
        ],
        [
            0.843035876750946,
            0.15696413815021515
        ],
        [
            0.9832947850227356,
            0.016705220565199852
        ],
        [
            0.998872697353363,
            0.0011272889096289873
        ],
        [
            0.9997112154960632,
            0.00028878371813334525
        ],
        [
            0.9999806880950928,
            1.925325886986684e-05
        ],
        [
            0.999745786190033,
            0.00025421674945391715
        ],
        [
            0.9995885491371155,
            0.00041143488488160074
        ],
        [
            0.9981887936592102,
            0.0018111761892214417
        ],
        [
            0.9956153631210327,
            0.0043846676126122475
        ],
        [
            0.9189667701721191,
            0.08103324472904205
        ],
        [
            0.6300218105316162,
            0.3699781596660614
        ],
        [
            7.884177929658523e-14,
            1.0
        ],
        [
            2.5397510483582408e-11,
            1.0
        ]
    ],
    "states": [
        1,
        1,
        1,
        1,
        1,
        1,
        1,
        1,
        1,
        1,
        1,
        1,
        1,
        1,
        1,
        1,
        1,
        1,
        1,
        1,
        1,
        1,
        1,
        1,
        1,
        1,
        1,
        1,
        1,
        1,
        1,
        1,
        1,
        1,
        1,
        1,
        1,
        1,
        1,
        1,
        1,
        1,
        1,
        1,
        1,
        1,
        1,
        1,
        1,
        1,
        1,
        1,
        1,
        1,
        1,
        1,
        1,
        1,
        1,
        1,
        1,
        1,
        1,
        1,
        1,
        1,
        1,
        1,
        0,
        1,
        1,
        1,
        0,
        1,
        1,
        1,
        1,
        1,
        1,
        1,
        1,
        1,
        1,
        1,
        1,
        1,
        0,
        0,
        0,
        0,
        0,
        0,
        0,
        0,
        0,
        0,
        0,
        0,
        0,
        0,
        0,
        0,
        0,
        1,
        1,
        1,
        1,
        0,
        0,
        0,
        0,
        0,
        0,
        0,
        0,
        0,
        0,
        0,
        0,
        0,
        0,
        0,
        0,
        0,
        0,
        0,
        0,
        1,
        1
    ],
    "observation_types": [
        "turning_angle",
        "speed"
    ],
    "obs_dist_params": {
        "turning_angle": {
            "vm_locs": [
                -0.015728473663330078,
                -0.03731822967529297
            ],
            "vm_cons": [
                1.0725607872009277,
                3.5960190296173096
            ]
        },
        "speed": {
            "gamma_shapes": [
                1.4652767181396484,
                3.5237374305725098
            ],
            "gamma_rates": [
                7.3383708000183105,
                6.654575347900391
            ]
        }
    },
    "log_likelihood": -126.5955810546875,
    "num_params": 14,
    "bayesian_information_criterion": 321.2285357704384,
    "covariate_types": [
        "temperature",
        "depth"
    ]
}