{
    "initial_probs": [
        0.9999384880065918,
        6.153307913336903e-05
    ],
    "initial_logits": [
        5.083408355712891,
        -4.612465858459473
    ],
    "regression_weights": [
        [
            [
                -0.0,
                13.634639739990234
            ],
            [
                4.8815598487854,
                -0.0
            ]
        ]
    ],
    "regression_intercepts": [
        [
            [
                0.0,
                -27.17665672302246
            ],
            [
                2.3165204524993896,
                -0.0
            ]
        ]
    ],
    "transition_probs": [
        [
            [
                2.2747237427012124e-09,
                1.0
            ],
            [
                1.0,
                4.71881955732556e-09
            ]
        ],
        [
            [
                2.3373889490585498e-09,
                1.0
            ],
            [
                1.0,
                4.764954653069253e-09
            ]
        ],
        [
            [
                2.466515658383628e-09,
                1.0
            ],
            [
                1.0,
                4.8575823363705695e-09
            ]
        ],
        [
            [
                2.6190101198864113e-09,
                1.0
            ],
            [
                1.0,
                4.963045086014972e-09
            ]
        ],
        [
            [
                2.7504531985300673e-09,
                1.0
            ],
            [
                1.0,
                5.050826423769195e-09
            ]
        ],
        [
            [
                2.885838901178772e-09,
                1.0
            ],
            [
                1.0,
                5.138463876619426e-09
            ]
        ],
        [
            [
                3.1355491536544378e-09,
                1.0
            ],
            [
                1.0,
                5.293432803199494e-09
            ]
        ],
        [
            [
                3.4188314401717435e-09,
                1.0
            ],
            [
                1.0,
                5.459912522098875e-09
            ]
        ],
        [
            [
                4.478908355309841e-09,
                1.0
            ],
            [
                1.0,
                6.014237552420809e-09
            ]
        ],
        [
            [
                5.440234041031999e-09,
                1.0
            ],
            [
                1.0,
                6.447844924650781e-09
            ]
        ],
        [
            [
                6.463001689382963e-09,
                1.0
            ],
            [
                1.0,
                6.8580416900942964e-09
            ]
        ],
        [
            [
                7.400827950476696e-09,
                1.0
            ],
            [
                1.0,
                7.1989512129277955e-09
            ]
        ],
        [
            [
                8.21920220772654e-09,
                1.0
            ],
            [
                1.0,
                7.474411312102802e-09
            ]
        ],
        [
            [
                8.938995321727816e-09,
                1.0
            ],
            [
                1.0,
                7.702471549464462e-09
            ]
        ],
        [
            [
                9.727981975515831e-09,
                1.0
            ],
            [
                1.0,
                7.939292778758045e-09
            ]
        ],
        [
            [
                1.0377765313762666e-08,
                1.0
            ],
            [
                1.0,
                8.125227601851748e-09
            ]
        ],
        [
            [
                1.1026991764140348e-08,
                1.0
            ],
            [
                1.0,
                8.303676857224218e-09
            ]
        ],
        [
            [
                1.200723165339923e-08,
                1.0
            ],
            [
                1.0,
                8.560779640731653e-09
            ]
        ],
        [
            [
                1.2805252858072436e-08,
                1.0
            ],
            [
                1.0,
                8.760282277364695e-09
            ]
        ],
        [
            [
                1.3463578696359946e-08,
                1.0
            ],
            [
                1.0,
                8.91893314758363e-09
            ]
        ],
        [
            [
                1.4239373236080155e-08,
                1.0
            ],
            [
                1.0,
                9.0996321588932e-09
            ]
        ],
        [
            [
                1.5682202203493034e-08,
                1.0
            ],
            [
                1.0,
                9.41957001288074e-09
            ]
        ],
        [
            [
                1.702098728628698e-08,
                1.0
            ],
            [
                1.0,
                9.699930636486442e-09
            ]
        ],
        [
            [
                1.837342011867804e-08,
                1.0
            ],
            [
                1.0,
                9.969126857356514e-09
            ]
        ],
        [
            [
                2.0061973415863577e-08,
                1.0
            ],
            [
                1.0,
                1.0287935836572615e-08
            ]
        ],
        [
            [
                2.1428570917692014e-08,
                1.0
            ],
            [
                1.0,
                1.0533534045009674e-08
            ]
        ],
        [
            [
                8.29872897156747e-06,
                0.9999917149543762
            ],
            [
                0.9999999403953552,
                8.895170111600237e-08
            ]
        ],
        [
            [
                3.4988144648195885e-07,
                0.9999996423721313
            ],
            [
                1.0,
                2.8630875448243387e-08
            ]
        ],
        [
            [
                6.551579281222075e-05,
                0.9999344944953918
            ],
            [
                0.9999998211860657,
                1.8639430265920964e-07
            ]
        ],
        [
            [
                6.5578378780628555e-06,
                0.9999934434890747
            ],
            [
                0.9999999403953552,
                8.176082388899886e-08
            ]
        ],
        [
            [
                0.0005014401976950467,
                0.9994985461235046
            ],
            [
                0.9999996423721313,
                3.863224833366985e-07
            ]
        ],
        [
            [
                0.010371973738074303,
                0.9896280169487
            ],
            [
                0.9999988675117493,
                1.1469043101897114e-06
            ]
        ],
        [
            [
                5.150238939677365e-05,
                0.9999485015869141
            ],
            [
                0.9999998211860657,
                1.710053822989721e-07
            ]
        ],
        [
            [
                5.808331479784101e-06,
                0.9999942183494568
            ],
            [
                0.9999999403953552,
                7.82842874968992e-08
            ]
        ],
        [
            [
                1.2799193882528925e-06,
                0.9999987483024597
            ],
            [
                0.9999998807907104,
                4.55509550079114e-08
            ]
        ],
        [
            [
                4.4615859451369033e-07,
                0.9999995827674866
            ],
            [
                0.9999999403953552,
                3.1234215214226424e-08
            ]
        ],
        [
            [
                2.2170699764956225e-07,
                0.9999997615814209
            ],
            [
                1.0,
                2.4316141988833806e-08
            ]
        ],
        [
            [
                2.7277701875050298e-08,
                1.0
            ],
            [
                1.0,
                1.148420381014148e-08
            ]
        ],
        [
            [
                9.459952707402408e-06,
                0.9999905228614807
            ],
            [
                0.9999998807907104,
                9.322200611450171e-08
            ]
        ],
        [
            [
                1.9719152533070883e-06,
                0.9999980330467224
            ],
            [
                1.0,
                5.3174179726056536e-08
            ]
        ],
        [
            [
                6.642823677793785e-07,
                0.9999993443489075
            ],
            [
                1.0,
                3.601803655328695e-08
            ]
        ],
        [
            [
                3.155987826630735e-07,
                0.9999997019767761
            ],
            [
                1.0,
                2.7593085150101615e-08
            ]
        ],
        [
            [
                1.9149338470469957e-07,
                0.9999998211860657
            ],
            [
                1.0,
                2.307358215603017e-08
            ]
        ],
        [
            [
                1.3857408021067386e-07,
                0.9999998807907104
            ],
            [
                1.0,
                2.0550505297478594e-08
            ]
        ],
        [
            [
                2.6154026272706687e-05,
                0.9999738335609436
            ],
            [
                0.9999998807907104,
                1.3416619992767664e-07
            ]
        ],
        [
            [
                0.0009134483989328146,
                0.9990865588188171
            ],
            [
                0.9999995231628418,
                4.789244485436939e-07
            ]
        ],
        [
            [
                0.010826780460774899,
                0.9891732335090637
            ],
            [
                0.9999988079071045,
                1.1648543249975774e-06
            ]
        ],
        [
            [
                0.05175216123461723,
                0.9482478499412537
            ],
            [
                0.9999979138374329,
                2.0705936094600474e-06
            ]
        ],
        [
            [
                0.17123733460903168,
                0.8287626504898071
            ],
            [
                0.9999966621398926,
                3.3349656405334827e-06
            ]
        ],
        [
            [
                0.3391672372817993,
                0.6608327627182007
            ],
            [
                0.9999954104423523,
                4.619197170541156e-06
            ]
        ],
        [
            [
                0.4900844991207123,
                0.5099154710769653
            ],
            [
                0.9999942183494568,
                5.782426796940854e-06
            ]
        ],
        [
            [
                0.5721630454063416,
                0.42783695459365845
            ],
            [
                0.9999935030937195,
                6.50841866445262e-06
            ]
        ],
        [
            [
                0.6485211253166199,
                0.35147884488105774
            ],
            [
                0.9999926686286926,
                7.303333859454142e-06
            ]
        ],
        [
            [
                0.6960757374763489,
                0.30392423272132874
            ],
            [
                0.9999921321868896,
                7.890925189713016e-06
            ]
        ],
        [
            [
                0.014565102756023407,
                0.985434889793396
            ],
            [
                0.9999986886978149,
                1.2971178193765809e-06
            ]
        ],
        [
            [
                0.0566411130130291,
                0.9433588981628418
            ],
            [
                0.9999978542327881,
                2.142566472684848e-06
            ]
        ],
        [
            [
                0.7278273701667786,
                0.27217262983322144
            ],
            [
                0.9999916553497314,
                8.341043212567456e-06
            ]
        ],
        [
            [
                0.016852132976055145,
                0.9831478595733643
            ],
            [
                0.9999986290931702,
                1.3677863535122015e-06
            ]
        ],
        [
            [
                0.07756772637367249,
                0.9224322438240051
            ],
            [
                0.9999975562095642,
                2.4171881705115084e-06
            ]
        ],
        [
            [
                0.19714058935642242,
                0.8028594255447388
            ],
            [
                0.9999964237213135,
                3.547577762219589e-06
            ]
        ],
        [
            [
                0.0033273263834416866,
                0.9966726899147034
            ],
            [
                0.9999992251396179,
                7.614538617417566e-07
            ]
        ],
        [
            [
                0.9846537709236145,
                0.015346250496804714
            ],
            [
                0.9999739527702332,
                2.602097811177373e-05
            ]
        ],
        [
            [
                0.9626786112785339,
                0.03732140362262726
            ],
            [
                0.9999812245368958,
                1.877737304312177e-05
            ]
        ],
        [
            [
                0.0865243673324585,
                0.9134756326675415
            ],
            [
                0.9999974966049194,
                2.522427394069382e-06
            ]
        ],
        [
            [
                0.0018866307800635695,
                0.9981133937835693
            ],
            [
                0.9999994039535522,
                6.211529353095102e-07
            ]
        ],
        [
            [
                0.00012602373317349702,
                0.9998739957809448
            ],
            [
                0.9999997615814209,
                2.3559121586913534e-07
            ]
        ],
        [
            [
                1.9138042262056842e-05,
                0.9999808669090271
            ],
            [
                0.9999998807907104,
                1.1997174453881598e-07
            ]
        ],
        [
            [
                0.0006497344584204257,
                0.9993502497673035
            ],
            [
                0.9999995827674866,
                4.2389387999719474e-07
            ]
        ],
        [
            [
                0.0058545274659991264,
                0.9941454529762268
            ],
            [
                0.9999990463256836,
                9.330317425337853e-07
            ]
        ],
        [
            [
                0.011493773199617863,
                0.9885061979293823
            ],
            [
                0.9999988079071045,
                1.1903430277016014e-06
            ]
        ],
        [
            [
                0.3502512276172638,
                0.6497488021850586
            ],
            [
                0.9999952912330627,
                4.701071247836808e-06
            ]
        ],
        [
            [
                0.007461279630661011,
                0.9925387501716614
            ],
            [
                0.9999989867210388,
                1.0182526466451236e-06
            ]
        ],
        [
            [
                0.03732037544250488,
                0.9626796245574951
            ],
            [
                0.999998152256012,
                1.8319464061278268e-06
            ]
        ],
        [
            [
                0.0018518426222726703,
                0.9981481432914734
            ],
            [
                0.9999994039535522,
                6.170194524202088e-07
            ]
        ],
        [
            [
                0.013951092027127743,
                0.9860489368438721
            ],
            [
                0.9999987483024597,
                1.2769834256687318e-06
            ]
        ],
        [
            [
                0.0006834978703409433,
                0.9993165135383606
            ],
            [
                0.9999995827674866,
                4.316579236274265e-07
            ]
        ],
        [
            [
                0.007026405539363623,
                0.9929735660552979
            ],
            [
                0.9999989867210388,
                9.964373930415604e-07
            ]
        ],
        [
            [
                0.030994025990366936,
                0.9690059423446655
            ],
            [
                0.9999982714653015,
                1.7100667264458025e-06
            ]
        ],
        [
            [
                0.00040773575892671943,
                0.9995922446250916
            ],
            [
                0.9999996423721313,
                3.587321089071338e-07
            ]
        ],
        [
            [
                1.9416811483097263e-05,
                0.9999805688858032
            ],
            [
                0.9999998807907104,
                1.2059439313816256e-07
            ]
        ],
        [
            [
                8.147536391334143e-06,
                0.9999918341636658
            ],
            [
                0.9999999403953552,
                8.836812526169524e-08
            ]
        ],
        [
            [
                4.4936127778782975e-06,
                0.9999955296516418
            ],
            [
                0.9999999403953552,
                7.141174052094357e-08
            ]
        ],
        [
            [
                3.0059372875257395e-06,
                0.9999970197677612
            ],
            [
                0.9999999403953552,
                6.183767453649125e-08
            ]
        ],
        [
            [
                2.5459544303885195e-06,
                0.9999974370002747
            ],
            [
                0.9999998807907104,
                5.826777993434007e-08
            ]
        ],
        [
            [
                2.3045229227136588e-06,
                0.9999976754188538
            ],
            [
                0.9999998807907104,
                5.6225932354436736e-08
            ]
        ],
        [
            [
                0.00012995621364098042,
                0.9998700618743896
            ],
            [
                0.9999997615814209,
                2.3819782768441655e-07
            ]
        ],
        [
            [
                0.0017982536228373647,
                0.9982017278671265
            ],
            [
                0.9999994039535522,
                6.10554309332656e-07
            ]
        ],
        [
            [
                0.0002920547849498689,
                0.9997079372406006
            ],
            [
                0.9999997019767761,
                3.1832377089813235e-07
            ]
        ],
        [
            [
                0.0026701753959059715,
                0.997329831123352
            ],
            [
                0.9999992847442627,
                7.036060196696781e-07
            ]
        ],
        [
            [
                0.013912627473473549,
                0.9860873818397522
            ],
            [
                0.9999987483024597,
                1.2757054719259031e-06
            ]
        ],
        [
            [
                0.045187294483184814,
                0.9548127055168152
            ],
            [
                0.9999980330467224,
                1.96756855075364e-06
            ]
        ],
        [
            [
                0.0031719168182462454,
                0.9968280792236328
            ],
            [
                0.9999992251396179,
                7.484820798708824e-07
            ]
        ],
        [
            [
                0.0004885784583166242,
                0.9995114207267761
            ],
            [
                0.9999996423721313,
                3.827437069503503e-07
            ]
        ],
        [
            [
                0.0001338724250672385,
                0.9998661279678345
            ],
            [
                0.9999997615814209,
                2.4074375915006385e-07
            ]
        ],
        [
            [
                1.0330356417398434e-05,
                0.9999896883964539
            ],
            [
                0.9999998807907104,
                9.620649876751486e-08
            ]
        ],
        [
            [
                9.450033758184873e-06,
                0.9999905228614807
            ],
            [
                0.9999998807907104,
                9.318697635762874e-08
            ]
        ],
        [
            [
                9.023620805237442e-06,
                0.9999909996986389
            ],
            [
                0.9999998807907104,
                9.165917447262473e-08
            ]
        ],
        [
            [
                9.026306543091778e-06,
                0.9999909996986389
            ],
            [
                0.9999998807907104,
                9.16687810104122e-08
            ]
        ],
        [
            [
                0.00015307149442378432,
                0.9998469352722168
            ],
            [
                0.9999997615814209,
                2.5257824631808035e-07
            ]
        ],
        [
            [
                0.0014656402636319399,
                0.9985343813896179
            ],
            [
                0.9999994039535522,
                5.673770147041068e-07
            ]
        ],
        [
            [
                0.010950153693556786,
                0.9890498518943787
            ],
            [
                0.9999988079071045,
                1.1696421324813855e-06
            ]
        ],
        [
            [
                0.033069200813770294,
                0.9669308066368103
            ],
            [
                0.9999982714653015,
                1.7515533272671746e-06
            ]
        ],
        [
            [
                0.06435010582208633,
                0.9356498718261719
            ],
            [
                0.9999977350234985,
                2.249321141789551e-06
            ]
        ],
        [
            [
                0.005983266979455948,
                0.994016706943512
            ],
            [
                0.9999990463256836,
                9.403701710652967e-07
            ]
        ],
        [
            [
                0.014574248343706131,
                0.9854257702827454
            ],
            [
                0.9999986886978149,
                1.2974135188414948e-06
            ]
        ],
        [
            [
                0.0002539381675887853,
                0.9997460842132568
            ],
            [
                0.9999997019767761,
                3.027734862826037e-07
            ]
        ],
        [
            [
                0.002109732013195753,
                0.997890293598175
            ],
            [
                0.9999993443489075,
                6.465636488428572e-07
            ]
        ],
        [
            [
                0.007097369059920311,
                0.9929026365280151
            ],
            [
                0.9999989867210388,
                1.0000560450862395e-06
            ]
        ],
        [
            [
                0.02655883878469467,
                0.9734411835670471
            ],
            [
                0.9999983906745911,
                1.6154405102497549e-06
            ]
        ],
        [
            [
                0.051759932190179825,
                0.9482400417327881
            ],
            [
                0.9999979138374329,
                2.0707120711449534e-06
            ]
        ],
        [
            [
                0.006290271412581205,
                0.9937097430229187
            ],
            [
                0.9999990463256836,
                9.574744126439327e-07
            ]
        ],
        [
            [
                0.0014454040210694075,
                0.9985545873641968
            ],
            [
                0.999999463558197,
                5.645557621392072e-07
            ]
        ],
        [
            [
                0.007472956087440252,
                0.9925270676612854
            ],
            [
                0.9999989867210388,
                1.0188276746703195e-06
            ]
        ],
        [
            [
                0.029892444610595703,
                0.9701075553894043
            ],
            [
                0.9999983310699463,
                1.6873675576789537e-06
            ]
        ],
        [
            [
                0.005145241506397724,
                0.994854748249054
            ],
            [
                0.9999991059303284,
                8.906457651391975e-07
            ]
        ],
        [
            [
                0.020311202853918076,
                0.979688823223114
            ],
            [
                0.9999985098838806,
                1.4641842653873027e-06
            ]
        ],
        [
            [
                0.038365088403224945,
                0.9616349339485168
            ],
            [
                0.999998152256012,
                1.8508646917325677e-06
            ]
        ],
        [
            [
                0.007058415561914444,
                0.9929415583610535
            ],
            [
                0.9999989867210388,
                9.980732329495368e-07
            ]
        ],
        [
            [
                0.0021489779464900494,
                0.9978510141372681
            ],
            [
                0.9999993443489075,
                6.508540195682144e-07
            ]
        ],
        [
            [
                0.0009576415177434683,
                0.9990423321723938
            ],
            [
                0.9999995231628418,
                4.871028522757115e-07
            ]
        ],
        [
            [
                0.000549908319953829,
                0.9994500875473022
            ],
            [
                0.9999995827674866,
                3.9930478124006186e-07
            ]
        ],
        [
            [
                0.00039947160985320807,
                0.9996005296707153
            ],
            [
                0.9999996423721313,
                3.5611085991149594e-07
            ]
        ],
        [
            [
                0.002333259442821145,
                0.9976667165756226
            ],
            [
                0.9999993443489075,
                6.703548933728598e-07
            ]
        ],
        [
            [
                0.01174157951027155,
                0.988258421421051
            ],
            [
                0.9999988079071045,
                1.1995761042271624e-06
            ]
        ],
        [
            [
                0.0037473193369805813,
                0.9962526559829712
            ],
            [
                0.9999992251396179,
                7.946802611513704e-07
            ]
        ],
        [
            [
                0.015910811722278595,
                0.984089195728302
            ],
            [
                0.9999986886978149,
                1.3394686675383127e-06
            ]
        ],
        [
            [
                0.6319141983985901,
                0.36808574199676514
            ],
            [
                0.9999929070472717,
                7.117205768736312e-06
            ]
        ],
        [
            [
                0.9827917218208313,
                0.017208227887749672
            ],
            [
                0.9999750256538391,
                2.495880653441418e-05
            ]
        ]
    ],
    "transition_logits": [
        [
            [
                0.0,
                19.90140724182129
            ],
            [
                19.171707153320312,
                -0.0
            ]
        ],
        [
            [
                0.0,
                19.874231338500977
            ],
            [
                19.161977767944336,
                -0.0
            ]
        ],
        [
            [
                0.0,
                19.820459365844727
            ],
            [
                19.142724990844727,
                -0.0
            ]
        ],
        [
            [
                0.0,
                19.760469436645508
            ],
            [
                19.121246337890625,
                -0.0
            ]
        ],
        [
            [
                0.0,
                19.71150016784668
            ],
            [
                19.103713989257812,
                -0.0
            ]
        ],
        [
            [
                0.0,
                19.663450241088867
            ],
            [
                19.086511611938477,
                -0.0
            ]
        ],
        [
            [
                0.0,
                19.580461502075195
            ],
            [
                19.056798934936523,
                -0.0
            ]
        ],
        [
            [
                0.0,
                19.493967056274414
            ],
            [
                19.025833129882812,
                -0.0
            ]
        ],
        [
            [
                0.0,
                19.223886489868164
            ],
            [
                18.929136276245117,
                -0.0
            ]
        ],
        [
            [
                0.0,
                19.029443740844727
            ],
            [
                18.859519958496094,
                -0.0
            ]
        ],
        [
            [
                0.0,
                18.8571720123291
            ],
            [
                18.79784393310547,
                -0.0
            ]
        ],
        [
            [
                0.0,
                18.7216739654541
            ],
            [
                18.749330520629883,
                -0.0
            ]
        ],
        [
            [
                0.0,
                18.616792678833008
            ],
            [
                18.711780548095703,
                -0.0
            ]
        ],
        [
            [
                0.0,
                18.5328426361084
            ],
            [
                18.681724548339844,
                -0.0
            ]
        ],
        [
            [
                0.0,
                18.448259353637695
            ],
            [
                18.65144157409668,
                -0.0
            ]
        ],
        [
            [
                0.0,
                18.38360023498535
            ],
            [
                18.628292083740234,
                -0.0
            ]
        ],
        [
            [
                0.0,
                18.322919845581055
            ],
            [
                18.6065673828125,
                -0.0
            ]
        ],
        [
            [
                0.0,
                18.237756729125977
            ],
            [
                18.576074600219727,
                -0.0
            ]
        ],
        [
            [
                0.0,
                18.173410415649414
            ],
            [
                18.553037643432617,
                -0.0
            ]
        ],
        [
            [
                0.0,
                18.12327766418457
            ],
            [
                18.53508949279785,
                -0.0
            ]
        ],
        [
            [
                0.0,
                18.0672550201416
            ],
            [
                18.515031814575195,
                -0.0
            ]
        ],
        [
            [
                0.0,
                17.970739364624023
            ],
            [
                18.48047637939453,
                -0.0
            ]
        ],
        [
            [
                0.0,
                17.888818740844727
            ],
            [
                18.451147079467773,
                -0.0
            ]
        ],
        [
            [
                0.0,
                17.812360763549805
            ],
            [
                18.42377281188965,
                -0.0
            ]
        ],
        [
            [
                0.0,
                17.72443962097168
            ],
            [
                18.39229393005371,
                -0.0
            ]
        ],
        [
            [
                0.0,
                17.658540725708008
            ],
            [
                18.368701934814453,
                -0.0
            ]
        ],
        [
            [
                0.0,
                11.699399948120117
            ],
            [
                16.235172271728516,
                -0.0
            ]
        ],
        [
            [
                0.0,
                14.865671157836914
            ],
            [
                17.3687801361084,
                -0.0
            ]
        ],
        [
            [
                0.0,
                9.633153915405273
            ],
            [
                15.495401382446289,
                -0.0
            ]
        ],
        [
            [
                0.0,
                11.934843063354492
            ],
            [
                16.319467544555664,
                -0.0
            ]
        ],
        [
            [
                0.0,
                7.597524642944336
            ],
            [
                14.766592979431152,
                -0.0
            ]
        ],
        [
            [
                0.0,
                4.558221817016602
            ],
            [
                13.67844295501709,
                -0.0
            ]
        ],
        [
            [
                0.0,
                9.873830795288086
            ],
            [
                15.581570625305176,
                -0.0
            ]
        ],
        [
            [
                0.0,
                12.056211471557617
            ],
            [
                16.362918853759766,
                -0.0
            ]
        ],
        [
            [
                0.0,
                13.56871223449707
            ],
            [
                16.904434204101562,
                -0.0
            ]
        ],
        [
            [
                0.0,
                14.622591018676758
            ],
            [
                17.28175163269043,
                -0.0
            ]
        ],
        [
            [
                0.0,
                15.321908950805664
            ],
            [
                17.53212547302246,
                -0.0
            ]
        ],
        [
            [
                0.0,
                17.41719627380371
            ],
            [
                18.28229331970215,
                -0.0
            ]
        ],
        [
            [
                0.0,
                11.56843376159668
            ],
            [
                16.188282012939453,
                -0.0
            ]
        ],
        [
            [
                0.0,
                13.136503219604492
            ],
            [
                16.749692916870117,
                -0.0
            ]
        ],
        [
            [
                0.0,
                14.224557876586914
            ],
            [
                17.139245986938477,
                -0.0
            ]
        ],
        [
            [
                0.0,
                14.968793869018555
            ],
            [
                17.40570068359375,
                -0.0
            ]
        ],
        [
            [
                0.0,
                15.468412399291992
            ],
            [
                17.584577560424805,
                -0.0
            ]
        ],
        [
            [
                0.0,
                15.791860580444336
            ],
            [
                17.700380325317383,
                -0.0
            ]
        ],
        [
            [
                0.0,
                10.551481246948242
            ],
            [
                15.824186325073242,
                -0.0
            ]
        ],
        [
            [
                0.0,
                6.997369766235352
            ],
            [
                14.551722526550293,
                -0.0
            ]
        ],
        [
            [
                0.0,
                4.5148468017578125
            ],
            [
                13.66291332244873,
                -0.0
            ]
        ],
        [
            [
                0.0,
                2.9081497192382812
            ],
            [
                13.08767318725586,
                -0.0
            ]
        ],
        [
            [
                0.0,
                1.576883316040039
            ],
            [
                12.611044883728027,
                -0.0
            ]
        ],
        [
            [
                0.0,
                0.6670074462890625
            ],
            [
                12.285284996032715,
                -0.0
            ]
        ],
        [
            [
                0.0,
                0.03966712951660156
            ],
            [
                12.060681343078613,
                -0.0
            ]
        ],
        [
            [
                0.0,
                -0.2906818389892578
            ],
            [
                11.942407608032227,
                -0.0
            ]
        ],
        [
            [
                0.0,
                -0.6125450134277344
            ],
            [
                11.82717227935791,
                -0.0
            ]
        ],
        [
            [
                0.0,
                -0.8286800384521484
            ],
            [
                11.749789237976074,
                -0.0
            ]
        ],
        [
            [
                0.0,
                4.214454650878906
            ],
            [
                13.555364608764648,
                -0.0
            ]
        ],
        [
            [
                0.0,
                2.812711715698242
            ],
            [
                13.05350399017334,
                -0.0
            ]
        ],
        [
            [
                0.0,
                -0.9836273193359375
            ],
            [
                11.694314002990723,
                -0.0
            ]
        ],
        [
            [
                0.0,
                4.066282272338867
            ],
            [
                13.502315521240234,
                -0.0
            ]
        ],
        [
            [
                0.0,
                2.475862503051758
            ],
            [
                12.932903289794922,
                -0.0
            ]
        ],
        [
            [
                0.0,
                1.4042625427246094
            ],
            [
                12.54924201965332,
                -0.0
            ]
        ],
        [
            [
                0.0,
                5.702253341674805
            ],
            [
                14.088035583496094,
                -0.0
            ]
        ],
        [
            [
                0.0,
                -4.161418914794922
            ],
            [
                10.556581497192383,
                -0.0
            ]
        ],
        [
            [
                0.0,
                -3.250152587890625
            ],
            [
                10.88283920288086,
                -0.0
            ]
        ],
        [
            [
                0.0,
                2.356830596923828
            ],
            [
                12.890286445617676,
                -0.0
            ]
        ],
        [
            [
                0.0,
                6.271074295043945
            ],
            [
                14.291687965393066,
                -0.0
            ]
        ],
        [
            [
                0.0,
                8.978914260864258
            ],
            [
                15.261167526245117,
                -0.0
            ]
        ],
        [
            [
                0.0,
                10.863813400268555
            ],
            [
                15.936009407043457,
                -0.0
            ]
        ],
        [
            [
                0.0,
                7.338296890258789
            ],
            [
                14.673782348632812,
                -0.0
            ]
        ],
        [
            [
                0.0,
                5.134668350219727
            ],
            [
                13.884825706481934,
                -0.0
            ]
        ],
        [
            [
                0.0,
                4.454389572143555
            ],
            [
                13.641267776489258,
                -0.0
            ]
        ],
        [
            [
                0.0,
                0.6179351806640625
            ],
            [
                12.267715454101562,
                -0.0
            ]
        ],
        [
            [
                0.0,
                4.890539169311523
            ],
            [
                13.7974214553833,
                -0.0
            ]
        ],
        [
            [
                0.0,
                3.250181198120117
            ],
            [
                13.210129737854004,
                -0.0
            ]
        ],
        [
            [
                0.0,
                6.28972053527832
            ],
            [
                14.298364639282227,
                -0.0
            ]
        ],
        [
            [
                0.0,
                4.258148193359375
            ],
            [
                13.571008682250977,
                -0.0
            ]
        ],
        [
            [
                0.0,
                7.287603378295898
            ],
            [
                14.655632019042969,
                -0.0
            ]
        ],
        [
            [
                0.0,
                4.951028823852539
            ],
            [
                13.81907844543457,
                -0.0
            ]
        ],
        [
            [
                0.0,
                3.442476272583008
            ],
            [
                13.278976440429688,
                -0.0
            ]
        ],
        [
            [
                0.0,
                7.804483413696289
            ],
            [
                14.840689659118652,
                -0.0
            ]
        ],
        [
            [
                0.0,
                10.84935188293457
            ],
            [
                15.930832862854004,
                -0.0
            ]
        ],
        [
            [
                0.0,
                11.71778678894043
            ],
            [
                16.24175453186035,
                -0.0
            ]
        ],
        [
            [
                0.0,
                12.312849044799805
            ],
            [
                16.454803466796875,
                -0.0
            ]
        ],
        [
            [
                0.0,
                12.71491813659668
            ],
            [
                16.598752975463867,
                -0.0
            ]
        ],
        [
            [
                0.0,
                12.881002426147461
            ],
            [
                16.65821647644043,
                -0.0
            ]
        ],
        [
            [
                0.0,
                12.980634689331055
            ],
            [
                16.69388771057129,
                -0.0
            ]
        ],
        [
            [
                0.0,
                8.948183059692383
            ],
            [
                15.250164031982422,
                -0.0
            ]
        ],
        [
            [
                0.0,
                6.31913948059082
            ],
            [
                14.308897972106934,
                -0.0
            ]
        ],
        [
            [
                0.0,
                8.138277053833008
            ],
            [
                14.960196495056152,
                -0.0
            ]
        ],
        [
            [
                0.0,
                5.922937393188477
            ],
            [
                14.167046546936035,
                -0.0
            ]
        ],
        [
            [
                0.0,
                4.260948181152344
            ],
            [
                13.572010040283203,
                -0.0
            ]
        ],
        [
            [
                0.0,
                3.050699234008789
            ],
            [
                13.138710021972656,
                -0.0
            ]
        ],
        [
            [
                0.0,
                5.750242233276367
            ],
            [
                14.105217933654785,
                -0.0
            ]
        ],
        [
            [
                0.0,
                7.62352180480957
            ],
            [
                14.775899887084961,
                -0.0
            ]
        ],
        [
            [
                0.0,
                8.918489456176758
            ],
            [
                15.239532470703125,
                -0.0
            ]
        ],
        [
            [
                0.0,
                11.480413436889648
            ],
            [
                16.156768798828125,
                -0.0
            ]
        ],
        [
            [
                0.0,
                11.569482803344727
            ],
            [
                16.188657760620117,
                -0.0
            ]
        ],
        [
            [
                0.0,
                11.615655899047852
            ],
            [
                16.205188751220703,
                -0.0
            ]
        ],
        [
            [
                0.0,
                11.615358352661133
            ],
            [
                16.2050838470459,
                -0.0
            ]
        ],
        [
            [
                0.0,
                8.784452438354492
            ],
            [
                15.191544532775879,
                -0.0
            ]
        ],
        [
            [
                0.0,
                6.523996353149414
            ],
            [
                14.382241249084473,
                -0.0
            ]
        ],
        [
            [
                0.0,
                4.503391265869141
            ],
            [
                13.658811569213867,
                -0.0
            ]
        ],
        [
            [
                0.0,
                3.3755245208740234
            ],
            [
                13.255005836486816,
                -0.0
            ]
        ],
        [
            [
                0.0,
                2.6769027709960938
            ],
            [
                13.00487995147705,
                -0.0
            ]
        ],
        [
            [
                0.0,
                5.112787246704102
            ],
            [
                13.876991271972656,
                -0.0
            ]
        ],
        [
            [
                0.0,
                4.213817596435547
            ],
            [
                13.555136680603027,
                -0.0
            ]
        ],
        [
            [
                0.0,
                8.278165817260742
            ],
            [
                15.01028060913086,
                -0.0
            ]
        ],
        [
            [
                0.0,
                6.159082412719727
            ],
            [
                14.251593589782715,
                -0.0
            ]
        ],
        [
            [
                0.0,
                4.940908432006836
            ],
            [
                13.81545352935791,
                -0.0
            ]
        ],
        [
            [
                0.0,
                3.6014747619628906
            ],
            [
                13.335901260375977,
                -0.0
            ]
        ],
        [
            [
                0.0,
                2.907991409301758
            ],
            [
                13.087615966796875,
                -0.0
            ]
        ],
        [
            [
                0.0,
                5.062440872192383
            ],
            [
                13.858965873718262,
                -0.0
            ]
        ],
        [
            [
                0.0,
                6.537919998168945
            ],
            [
                14.387226104736328,
                -0.0
            ]
        ],
        [
            [
                0.0,
                4.88896369934082
            ],
            [
                13.796856880187988,
                -0.0
            ]
        ],
        [
            [
                0.0,
                3.4798011779785156
            ],
            [
                13.292339324951172,
                -0.0
            ]
        ],
        [
            [
                0.0,
                5.264524459838867
            ],
            [
                13.931318283081055,
                -0.0
            ]
        ],
        [
            [
                0.0,
                3.8760623931884766
            ],
            [
                13.434210777282715,
                -0.0
            ]
        ],
        [
            [
                0.0,
                3.221487045288086
            ],
            [
                13.19985580444336,
                -0.0
            ]
        ],
        [
            [
                0.0,
                4.946451187133789
            ],
            [
                13.817438125610352,
                -0.0
            ]
        ],
        [
            [
                0.0,
                6.14061164855957
            ],
            [
                14.244979858398438,
                -0.0
            ]
        ],
        [
            [
                0.0,
                6.950078964233398
            ],
            [
                14.5347900390625,
                -0.0
            ]
        ],
        [
            [
                0.0,
                7.505208969116211
            ],
            [
                14.733540534973145,
                -0.0
            ]
        ],
        [
            [
                0.0,
                7.824968338012695
            ],
            [
                14.848023414611816,
                -0.0
            ]
        ],
        [
            [
                0.0,
                6.05815315246582
            ],
            [
                14.215457916259766,
                -0.0
            ]
        ],
        [
            [
                0.0,
                4.432807922363281
            ],
            [
                13.633541107177734,
                -0.0
            ]
        ],
        [
            [
                0.0,
                5.58296012878418
            ],
            [
                14.04532527923584,
                -0.0
            ]
        ],
        [
            [
                0.0,
                4.124717712402344
            ],
            [
                13.523236274719238,
                -0.0
            ]
        ],
        [
            [
                0.0,
                -0.5404376983642578
            ],
            [
                11.852988243103027,
                -0.0
            ]
        ],
        [
            [
                0.0,
                -4.045009613037109
            ],
            [
                10.598258972167969,
                -0.0
            ]
        ]
    ],
    "posterior_probs": [
        [
            1.0,
            3.168835679967508e-11
        ],
        [
            3.1484245766044694e-11,
            1.0
        ],
        [
            1.0,
            3.13299317045157e-11
        ],
        [
            3.122969938207376e-11,
            1.0
        ],
        [
            1.0,
            3.1255921462136627e-11
        ],
        [
            3.116329416741337e-11,
            1.0
        ],
        [
            1.0,
            3.11058123703134e-11
        ],
        [
            3.0604407896817065e-11,
            1.0
        ],
        [
            1.0,
            3.033891887715967e-11
        ],
        [
            2.9966248232815573e-11,
            1.0
        ],
        [
            1.0,
            3.0497888936498185e-11
        ],
        [
            3.167578699336815e-11,
            1.0
        ],
        [
            1.0,
            3.281145147249198e-11
        ],
        [
            3.418469327054474e-11,
            1.0
        ],
        [
            1.0,
            3.895386443963922e-11
        ],
        [
            4.213491708315864e-11,
            1.0
        ],
        [
            1.0,
            4.426393626633107e-11
        ],
        [
            4.6595356045786573e-11,
            1.0
        ],
        [
            1.0,
            5.540516656576955e-11
        ],
        [
            7.167445803535344e-11,
            1.0
        ],
        [
            1.0,
            9.008666035370538e-11
        ],
        [
            1.1912891506593581e-10,
            1.0
        ],
        [
            1.0,
            1.3709144930373895e-10
        ],
        [
            1.4793406777346974e-10,
            1.0
        ],
        [
            1.0,
            1.5395625052594397e-10
        ],
        [
            1.695800722067986e-10,
            1.0
        ],
        [
            1.0,
            1.793720727505388e-10
        ],
        [
            4.812734655246231e-09,
            1.0
        ],
        [
            1.0,
            4.839059819516933e-09
        ],
        [
            8.965243125658162e-08,
            0.9999998807907104
        ],
        [
            0.9999998807907104,
            9.036799042405619e-08
        ],
        [
            1.366257947665872e-05,
            0.9999862909317017
        ],
        [
            0.9999964237213135,
            3.5469074646243826e-06
        ],
        [
            3.8013581615814473e-06,
            0.9999961853027344
        ],
        [
            0.9999961853027344,
            3.7956779124215245e-06
        ],
        [
            3.7994734611856984e-06,
            0.9999961853027344
        ],
        [
            0.9999961853027344,
            3.79979223907867e-06
        ],
        [
            3.8033306282159174e-06,
            0.9999961853027344
        ],
        [
            0.9999961853027344,
            3.803824029091629e-06
        ],
        [
            5.0564958655741066e-06,
            0.9999949932098389
        ],
        [
            0.9999948740005493,
            5.074117780168308e-06
        ],
        [
            5.330138264980633e-06,
            0.9999946355819702
        ],
        [
            0.9999946355819702,
            5.347245405573631e-06
        ],
        [
            5.478020284499507e-06,
            0.9999945163726807
        ],
        [
            0.9999945163726807,
            5.489609520736849e-06
        ],
        [
            1.9976265321020037e-05,
            0.9999799728393555
        ],
        [
            0.9999798536300659,
            2.016891448874958e-05
        ],
        [
            0.012630181387066841,
            0.9873698353767395
        ],
        [
            0.9881687760353088,
            0.01183124165982008
        ],
        [
            0.22765710949897766,
            0.7723429203033447
        ],
        [
            0.843126654624939,
            0.15687328577041626
        ],
        [
            0.7729969024658203,
            0.22700311243534088
        ],
        [
            0.662451982498169,
            0.33754807710647583
        ],
        [
            0.8892616629600525,
            0.11073833703994751
        ],
        [
            0.4818347990512848,
            0.5181652307510376
        ],
        [
            0.5293793678283691,
            0.47062069177627563
        ],
        [
            0.501739501953125,
            0.498260498046875
        ],
        [
            0.9569172263145447,
            0.04308278113603592
        ],
        [
            0.046460606157779694,
            0.9535393714904785
        ],
        [
            0.9593380093574524,
            0.040661994367837906
        ],
        [
            0.2512284219264984,
            0.748771607875824
        ],
        [
            0.7497648596763611,
            0.25023511052131653
        ],
        [
            0.9930446743965149,
            0.006955289747565985
        ],
        [
            0.9967907071113586,
            0.0032092288602143526
        ],
        [
            0.01323168445378542,
            0.9867683053016663
        ],
        [
            0.9869891405105591,
            0.013010885566473007
        ],
        [
            0.013045025058090687,
            0.9869549870491028
        ],
        [
            0.9869558811187744,
            0.013044040650129318
        ],
        [
            0.013378416188061237,
            0.986621618270874
        ],
        [
            0.9867447018623352,
            0.013255313970148563
        ],
        [
            0.018656456843018532,
            0.9813435673713684
        ],
        [
            0.997530996799469,
            0.0024690127465873957
        ],
        [
            0.0035108625888824463,
            0.9964891672134399
        ],
        [
            0.9986623525619507,
            0.0013376105343922973
        ],
        [
            0.0013822956243529916,
            0.9986176490783691
        ],
        [
            0.9992393255233765,
            0.0007606876897625625
        ],
        [
            0.0007687679026275873,
            0.999231219291687
        ],
        [
            0.9999858140945435,
            1.4143884982331656e-05
        ],
        [
            2.302775828866288e-05,
            0.9999769926071167
        ],
        [
            0.9999994039535522,
            5.835598244630091e-07
        ],
        [
            5.806818990095053e-07,
            0.9999994039535522
        ],
        [
            0.9999995231628418,
            5.026303711019864e-07
        ],
        [
            5.026955705034197e-07,
            0.9999995231628418
        ],
        [
            0.9999995231628418,
            4.829620365853771e-07
        ],
        [
            4.835630420529924e-07,
            0.9999995231628418
        ],
        [
            0.9999995231628418,
            4.851742119171831e-07
        ],
        [
            9.495292033534497e-06,
            0.9999904632568359
        ],
        [
            0.999990701675415,
            9.31753766053589e-06
        ],
        [
            2.7607629817794077e-05,
            0.9999723434448242
        ],
        [
            0.9999735355377197,
            2.6480440283194184e-05
        ],
        [
            0.0010652710916474462,
            0.9989346861839294
        ],
        [
            0.9996023774147034,
            0.0003976547159254551
        ],
        [
            0.0005942793795838952,
            0.9994057416915894
        ],
        [
            0.9994082450866699,
            0.00059175631031394
        ],
        [
            0.0006086142966523767,
            0.9993913173675537
        ],
        [
            0.9993914365768433,
            0.0006085679051466286
        ],
        [
            0.0006099754828028381,
            0.9993900060653687
        ],
        [
            0.9993900060653687,
            0.000609970826189965
        ],
        [
            0.0006119226454757154,
            0.9993880987167358
        ],
        [
            0.999388575553894,
            0.0006114050047472119
        ],
        [
            0.0009386838064529002,
            0.9990612864494324
        ],
        [
            0.9991682767868042,
            0.0008317421306855977
        ],
        [
            0.005790545139461756,
            0.9942094087600708
        ],
        [
            0.9975407123565674,
            0.0024592983536422253
        ],
        [
            0.00282285432331264,
            0.9971771240234375
        ],
        [
            0.9977362155914307,
            0.0022637576330453157
        ],
        [
            0.002284078625962138,
            0.997715950012207
        ],
        [
            0.9977599382400513,
            0.002240016357973218
        ],
        [
            0.0036995396949350834,
            0.996300458908081
        ],
        [
            0.9971520900726318,
            0.0028479413595050573
        ],
        [
            0.01783871091902256,
            0.982161283493042
        ],
        [
            0.9825555086135864,
            0.017444444820284843
        ],
        [
            0.017861850559711456,
            0.9821381568908691
        ],
        [
            0.9826781153678894,
            0.01732194982469082
        ],
        [
            0.021815987303853035,
            0.9781840443611145
        ],
        [
            0.9789003133773804,
            0.021099647507071495
        ],
        [
            0.023794688284397125,
            0.9762052893638611
        ],
        [
            0.9822940826416016,
            0.017705928534269333
        ],
        [
            0.018527409061789513,
            0.9814726114273071
        ],
        [
            0.9818664193153381,
            0.01813354715704918
        ],
        [
            0.018254021182656288,
            0.9817459583282471
        ],
        [
            0.9818496108055115,
            0.01815040037035942
        ],
        [
            0.018293028697371483,
            0.9817070364952087
        ],
        [
            0.9817969799041748,
            0.018202954903244972
        ],
        [
            0.025328898802399635,
            0.9746710658073425
        ],
        [
            0.9748613834381104,
            0.02513861283659935
        ],
        [
            0.04507296159863472,
            0.9549270272254944
        ],
        [
            0.986764669418335,
            0.013235270045697689
        ],
        [
            0.9884372353553772,
            0.011562692932784557
        ]
    ],
    "states": [
        0,
        1,
        0,
        1,
        0,
        1,
        0,
        1,
        0,
        1,
        0,
        1,
        0,
        1,
        0,
        1,
        0,
        1,
        0,
        1,
        0,
        1,
        0,
        1,
        0,
        1,
        0,
        1,
        0,
        1,
        0,
        1,
        0,
        1,
        0,
        1,
        0,
        1,
        0,
        1,
        0,
        1,
        0,
        1,
        0,
        1,
        0,
        1,
        0,
        1,
        0,
        0,
        0,
        0,
        1,
        0,
        0,
        0,
        1,
        0,
        1,
        0,
        0,
        0,
        1,
        0,
        1,
        0,
        1,
        0,
        1,
        0,
        1,
        0,
        1,
        0,
        1,
        0,
        1,
        0,
        1,
        0,
        1,
        0,
        1,
        0,
        1,
        0,
        1,
        0,
        1,
        0,
        1,
        0,
        1,
        0,
        1,
        0,
        1,
        0,
        1,
        0,
        1,
        0,
        1,
        0,
        1,
        0,
        1,
        0,
        1,
        0,
        1,
        0,
        1,
        0,
        1,
        0,
        1,
        0,
        1,
        0,
        1,
        0,
        1,
        0,
        1,
        0,
        0
    ],
    "observation_types": [
        "turning_angle",
        "speed"
    ],
    "obs_dist_params": {
        "turning_angle": {
            "vm_locs": [
                -0.043882131576538086,
                0.17798757553100586
            ],
            "vm_cons": [
                3.727675676345825,
                3.7933638095855713
            ]
        },
        "speed": {
            "gamma_shapes": [
                7.496072292327881,
                4.143847942352295
            ],
            "gamma_rates": [
                12.68012523651123,
                8.323246955871582
            ]
        }
    },
    "covariate_types": [
        "temperature"
    ]
}